gdoc/__init__.py
gdoc/__main__.py
gdoc/app/__init__.py
gdoc/app/compile/__init__.py
gdoc/app/compile/command.py
gdoc/app/dump/__init__.py
gdoc/app/dump/command.py
gdoc/app/trace/__init__.py
gdoc/app/trace/command.py
gdoc/lib/__init__.py
gdoc/lib/debug.py
gdoc/lib/gdoc/__init__.py
gdoc/lib/gdoc/blocktag.py
gdoc/lib/gdoc/code.py
gdoc/lib/gdoc/config.py
gdoc/lib/gdoc/document.py
gdoc/lib/gdoc/section.py
gdoc/lib/gdoc/string.py
gdoc/lib/gdoc/text.py
gdoc/lib/gdoc/textblock.py
gdoc/lib/gdoc/textstring.py
gdoc/lib/gdoccompiler/__init__.py
gdoc/lib/gdoccompiler/gdcompiler/__init__.py
gdoc/lib/gdoccompiler/gdcompiler/gdcompiler.py
gdoc/lib/gdoccompiler/gdexception.py
gdoc/lib/gdocparser/__init__.py
gdoc/lib/gdocparser/documentparser.py
gdoc/lib/gdocparser/fsm.py
gdoc/lib/gdocparser/sectionparser.py
gdoc/lib/gdocparser/tag/blocktagparser.py
gdoc/lib/gdocparser/tag/inlinetagparser.py
gdoc/lib/gdocparser/tag/objecttaginfoparser.py
gdoc/lib/gdocparser/textblock/__init__.py
gdoc/lib/gdocparser/textblock/lineparser.py
gdoc/lib/gdocparser/textblock/textblockparser.py
gdoc/lib/gdocparser/textblock/texttokenizer.py
gdoc/lib/gdom.py
gdoc/lib/gdsymbol.py
gdoc/lib/gobj/__init__.py
gdoc/lib/gobj/gdobject.py
gdoc/lib/gobj/gdsymbol.py
gdoc/lib/gobj/gdsymboltable.py
gdoc/lib/gobj/types/__init__.py
gdoc/lib/gobj/types/baseobject.py
gdoc/lib/gobj/types/category.py
gdoc/lib/gobj/types/document.py
gdoc/lib/gobj/types/importobject.py
gdoc/lib/gobj/types/package.py
gdoc/lib/pandoc.py
gdoc/lib/pandocast/__init__.py
gdoc/lib/pandocast/pandocast.py
gdoc/lib/pandocastobject/__init__.py
gdoc/lib/pandocastobject/pandoc/__init__.py
gdoc/lib/pandocastobject/pandoc/pandoc.py
gdoc/lib/pandocastobject/pandocast/__init__.py
gdoc/lib/pandocastobject/pandocast/block.py
gdoc/lib/pandocastobject/pandocast/blocklist.py
gdoc/lib/pandocastobject/pandocast/element.py
gdoc/lib/pandocastobject/pandocast/inline.py
gdoc/lib/pandocastobject/pandocast/inlinelist.py
gdoc/lib/pandocastobject/pandocast/pandoc.py
gdoc-0.1.1.dist-info/entry_points.txt
gdoc-0.1.1.dist-info/LICENSE
gdoc-0.1.1.dist-info/WHEEL
gdoc-0.1.1.dist-info/METADATA
gdoc-0.1.1.dist-info/RECORD
