Metadata-Version: 2.1
Name: gdoc
Version: 0.1.1
Summary: A tool to process GDML(GDoc Markup Language) documents.
License: MIT
Author: Tsuyoshi Kodama
Author-email: tsuyoshi.kodama@byrnison.com
Requires-Python: >=3.10,<4.0
Classifier: License :: OSI Approved :: MIT License
Classifier: Programming Language :: Python :: 3
Classifier: Programming Language :: Python :: 3.10
Classifier: Programming Language :: Python :: 3.11
